MANIFEST.in
README
README.md
setup.cfg
setup.py
ofxmate/__init__.py
ofxmate/server.py
ofxmate/version.py
ofxmate.egg-info/PKG-INFO
ofxmate.egg-info/SOURCES.txt
ofxmate.egg-info/dependency_links.txt
ofxmate.egg-info/entry_points.txt
ofxmate.egg-info/not-zip-safe
ofxmate.egg-info/requires.txt
ofxmate.egg-info/top_level.txt
ofxmate/webapp/__init__.py
ofxmate/webapp/__init__.pyc
ofxmate/webapp/html/__init__.py
ofxmate/webapp/html/base.html
ofxmate/webapp/html/favicon.ico
ofxmate/webapp/html/index.html
ofxmate/webapp/html/search.html
ofxmate/webapp/html/search_box.html
ofxmate/webapp/html/static/__init__.py
ofxmate/webapp/html/static/css/__init__.py
ofxmate/webapp/html/static/css/pepper-grinder/jquery-ui-1.8.23.custom.css
ofxmate/webapp/html/static/css/pepper-grinder/images/ui-bg_diagonal-maze_20_6e4f1c_10x10.png
ofxmate/webapp/html/static/css/pepper-grinder/images/ui-bg_diagonal-maze_40_000000_10x10.png
ofxmate/webapp/html/static/css/pepper-grinder/images/ui-bg_fine-grain_10_eceadf_60x60.png
ofxmate/webapp/html/static/css/pepper-grinder/images/ui-bg_fine-grain_10_f8f7f6_60x60.png
ofxmate/webapp/html/static/css/pepper-grinder/images/ui-bg_fine-grain_15_eceadf_60x60.png
ofxmate/webapp/html/static/css/pepper-grinder/images/ui-bg_fine-grain_15_f7f3de_60x60.png
ofxmate/webapp/html/static/css/pepper-grinder/images/ui-bg_fine-grain_15_ffffff_60x60.png
ofxmate/webapp/html/static/css/pepper-grinder/images/ui-bg_fine-grain_65_654b24_60x60.png
ofxmate/webapp/html/static/css/pepper-grinder/images/ui-bg_fine-grain_68_b83400_60x60.png
ofxmate/webapp/html/static/css/pepper-grinder/images/ui-icons_222222_256x240.png
ofxmate/webapp/html/static/css/pepper-grinder/images/ui-icons_3572ac_256x240.png
ofxmate/webapp/html/static/css/pepper-grinder/images/ui-icons_8c291d_256x240.png
ofxmate/webapp/html/static/css/pepper-grinder/images/ui-icons_b83400_256x240.png
ofxmate/webapp/html/static/css/pepper-grinder/images/ui-icons_fbdb93_256x240.png
ofxmate/webapp/html/static/css/pepper-grinder/images/ui-icons_ffffff_256x240.png
ofxmate/webapp/html/static/js/jquery-1.7.2.min.js
ofxmate/webapp/html/static/js/jquery-1.8.0.min.js
ofxmate/webapp/html/static/js/jquery-ui-1.8.23.custom.min.js