Metadata-Version: 1.0
Name: ofxmate
Version: 1.0.1
Summary: OFX client for dowloading transactions from banks
Home-page: https://github.com/captin411/ofxmate
Author: David Bartle
Author-email: captindave@gmail.com
License: MIT License
Keywords: ofx,Open Financial Exchange,download transactions
Platform: UNKNOWN
Classifier: Development Status :: 4 - Beta
Classifier: Intended Audience :: Developers
Classifier: Natural Language :: English
Classifier: Operating System :: OS Independent
Classifier: Programming Language :: Python
Classifier: Topic :: Software Development :: Libraries :: Python Modules
Classifier: Topic :: Utilities
Classifier: License :: OSI Approved :: MIT License
